README.rst
setup.py
_42/_42.py
_42/__init__.py
python_42.egg-info/PKG-INFO
python_42.egg-info/SOURCES.txt
python_42.egg-info/dependency_links.txt
python_42.egg-info/top_level.txt