Metadata-Version: 1.0
Name: python-42
Version: 0.1.2
Summary: Decorator that runs everything (in its way)
Home-page: http://github.com/marcorosa/_42
Author: Marco Rosa
Author-email: marcor165@hotmail.it
License: MIT
Keywords: decorator
Platform: UNKNOWN
